{"EAN":"5054267000247","Name":"Lucozade Energy Orange 6 X 380Ml Pack","TescoProductId":251603179,"TescoClientId":251603179,"TescoBaseProductId":55648912,"Image":"https://img.tesco.com/Groceries/pi/247/5054267000247/IDShot_110x110.jpg","TescoPermanentlyUnavailable":false,"PriceHistory":[{"Supermarket":0,"Price":3.7,"Checked":"2017-07-17T16:13:18.396713+01:00"},{"Supermarket":0,"Price":3.7,"Checked":"2017-07-20T17:14:15.797451+01:00"},{"Supermarket":0,"Price":3.7,"Checked":"2017-07-21T14:45:18.775606+01:00"},{"Supermarket":0,"Price":3.7,"Checked":"2017-07-24T12:37:13.102803+01:00"},{"Supermarket":0,"Price":3.7,"Checked":"2017-07-25T10:26:47.603406+01:00"},{"Supermarket":0,"Price":3.7,"Checked":"2017-07-26T10:34:22.447151+01:00"},{"Supermarket":0,"Price":3.7,"Checked":"2017-07-27T16:00:34.551617+01:00"},{"Supermarket":0,"Price":3.7,"Checked":"2017-07-28T13:23:14.966984+01:00"},{"Supermarket":0,"Price":3.7,"Checked":"2017-07-31T16:12:31.128539+01:00"},{"Supermarket":0,"Price":2.0,"Checked":"2017-08-01T08:53:46.24018+01:00"},{"Supermarket":0,"Price":2.0,"Checked":"2017-08-02T09:37:24.925004+01:00"},{"Supermarket":0,"Price":2.0,"Checked":"2017-08-03T09:37:23.241173+01:00"},{"Supermarket":0,"Price":2.0,"Checked":"2017-08-04T10:11:14.685876+01:00"},{"Supermarket":0,"Price":2.0,"Checked":"2017-08-07T09:16:44.549949+01:00"},{"Supermarket":0,"Price":2.0,"Checked":"2017-08-08T15:00:47.693086+01:00"}]}