{"EAN":"3073780828628","Name":"Mini Babybel Full Fat Soft Cheese 120G Pack","TescoProductId":253780736,"TescoClientId":253780736,"TescoBaseProductId":51333945,"Image":"https://img.tesco.com/Groceries/pi/628/3073780828628/IDShot_110x110.jpg","TescoPermanentlyUnavailable":false,"PriceHistory":[{"Supermarket":0,"Price":1.95,"Checked":"2017-07-28T13:28:22.400189+01:00"},{"Supermarket":0,"Price":1.95,"Checked":"2017-07-27T15:59:28.142312+01:00"},{"Supermarket":0,"Price":1.95,"Checked":"2017-07-27T15:59:17.32191+01:00"},{"Supermarket":0,"Price":1.95,"Checked":"2017-07-27T10:14:09.494169+01:00"},{"Supermarket":0,"Price":1.95,"Checked":"2017-07-26T10:38:43.847879+01:00"},{"Supermarket":0,"Price":1.95,"Checked":"2017-07-25T10:29:11.887697+01:00"},{"Supermarket":0,"Price":1.95,"Checked":"2017-07-24T12:40:07.872093+01:00"},{"Supermarket":0,"Price":1.95,"Checked":"2017-07-23T20:33:07.465703+01:00"},{"Supermarket":0,"Price":1.95,"Checked":"2017-07-21T14:43:51.091492+01:00"},{"Supermarket":0,"Price":1.95,"Checked":"2017-07-21T14:43:30.161666+01:00"},{"Supermarket":0,"Price":1.95,"Checked":"2017-07-17T10:42:17.299371+01:00"},{"Supermarket":0,"Price":1.95,"Checked":"2017-07-17T10:42:19.955665+01:00"},{"Supermarket":0,"Price":1.95,"Checked":"2017-07-17T11:17:18.170206+01:00"},{"Supermarket":0,"Price":1.95,"Checked":"2017-07-17T11:17:19.414405+01:00"},{"Supermarket":0,"Price":1.95,"Checked":"2017-07-17T16:12:14.137492+01:00"},{"Supermarket":0,"Price":1.95,"Checked":"2017-07-17T16:12:19.11575+01:00"},{"Supermarket":0,"Price":1.95,"Checked":"2017-07-20T10:14:01.064419+01:00"},{"Supermarket":0,"Price":1.95,"Checked":"2017-07-20T15:18:32.094695+01:00"},{"Supermarket":0,"Price":1.95,"Checked":"2017-07-20T15:18:47.911108+01:00"},{"Supermarket":0,"Price":1.95,"Checked":"2017-07-20T17:11:55.527208+01:00"},{"Supermarket":0,"Price":1.95,"Checked":"2017-07-20T17:12:22.78618+01:00"}]}