{"EAN":"8410441512956","Name":"Faustino Gran Reserva 75Cl","TescoProductId":254181286,"TescoClientId":254181286,"TescoBaseProductId":57069281,"Image":"https://img.tesco.com/Groceries/pi/956/8410441512956/IDShot_110x110.jpg","TescoPermanentlyUnavailable":false,"PriceHistory":[{"Supermarket":0,"Price":15.5,"Checked":"2017-08-01T08:58:45.922666+01:00"},{"Supermarket":0,"Price":15.5,"Checked":"2017-08-02T09:18:34.816823+01:00"},{"Supermarket":0,"Price":15.5,"Checked":"2017-08-03T09:44:04.024671+01:00"}]}