{"EAN":"5010204505442","Name":"Tesco Finest Camembert 250 G","TescoProductId":254490415,"TescoClientId":254490415,"TescoBaseProductId":57224495,"Image":"https://img.tesco.com/Groceries/pi/442/5010204505442/IDShot_110x110.jpg","TescoPermanentlyUnavailable":false,"PriceHistory":[{"Supermarket":0,"Price":2.25,"Checked":"2017-07-28T13:42:12.835449+01:00"},{"Supermarket":0,"Price":2.25,"Checked":"2017-08-01T10:27:04.404114+01:00"},{"Supermarket":0,"Price":2.25,"Checked":"2017-08-02T09:48:13.353007+01:00"},{"Supermarket":0,"Price":2.25,"Checked":"2017-08-03T09:52:23.704451+01:00"},{"Supermarket":0,"Price":2.25,"Checked":"2017-08-04T10:02:47.939132+01:00"},{"Supermarket":0,"Price":2.25,"Checked":"2017-08-07T10:05:04.178279+01:00"},{"Supermarket":0,"Price":2.25,"Checked":"2017-08-08T14:42:16.88766+01:00"},{"Supermarket":0,"Price":2.25,"Checked":"2017-08-09T15:02:11.094832+01:00"}]}