{"EAN":"5449000009289","Name":"Coca Cola Regular (Gb) 12 X 330Ml","TescoProductId":254855751,"TescoClientId":254855751,"TescoBaseProductId":50703256,"Image":"https://img.tesco.com/Groceries/pi/289/5449000009289/IDShot_110x110.jpg","TescoPermanentlyUnavailable":false,"PriceHistory":[{"Supermarket":0,"Price":4.0,"Checked":"2017-07-25T10:30:25.784217+01:00"},{"Supermarket":0,"Price":4.0,"Checked":"2017-07-24T12:41:17.690142+01:00"},{"Supermarket":0,"Price":4.0,"Checked":"2017-07-23T20:35:57.961946+01:00"},{"Supermarket":0,"Price":4.0,"Checked":"2017-07-21T09:01:46.562287+01:00"},{"Supermarket":0,"Price":4.0,"Checked":"2017-07-17T10:42:38.498442+01:00"},{"Supermarket":0,"Price":4.0,"Checked":"2017-07-17T10:42:47.787521+01:00"},{"Supermarket":0,"Price":4.0,"Checked":"2017-07-20T10:14:59.334864+01:00"}]}