{"EAN":"5012427043800","Name":"Fray Bentos Chicken And Mushroom Pie 475G","TescoProductId":255076853,"TescoClientId":255076853,"TescoBaseProductId":50585757,"Image":"https://img.tesco.com/Groceries/pi/800/5012427043800/IDShot_110x110.jpg","TescoPermanentlyUnavailable":false,"PriceHistory":[{"Supermarket":0,"Price":2.49,"Checked":"2017-08-02T09:34:00.793976+01:00"},{"Supermarket":0,"Price":2.49,"Checked":"2017-08-03T09:32:16.139467+01:00"},{"Supermarket":0,"Price":2.49,"Checked":"2017-08-04T10:23:20.309763+01:00"},{"Supermarket":0,"Price":2.49,"Checked":"2017-08-07T09:25:40.724607+01:00"},{"Supermarket":0,"Price":2.49,"Checked":"2017-08-08T15:42:08.391647+01:00"}]}