{"EAN":"5010003000339","Name":"Hovis Wholemeal Medium Bread 800G","TescoProductId":255000362,"TescoClientId":255000362,"TescoBaseProductId":50994601,"Image":"https://img.tesco.com/Groceries/pi/339/5010003000339/IDShot_110x110.jpg","TescoPermanentlyUnavailable":false,"PriceHistory":[{"Supermarket":0,"Price":1.0,"Checked":"2017-07-17T16:12:30.920187+01:00"},{"Supermarket":0,"Price":1.0,"Checked":"2017-07-20T17:13:00.420823+01:00"},{"Supermarket":0,"Price":1.0,"Checked":"2017-07-21T14:53:42.508585+01:00"},{"Supermarket":0,"Price":1.0,"Checked":"2017-07-24T12:42:29.825286+01:00"},{"Supermarket":0,"Price":1.0,"Checked":"2017-07-25T10:31:31.820564+01:00"},{"Supermarket":0,"Price":1.0,"Checked":"2017-07-26T10:43:00.727076+01:00"},{"Supermarket":0,"Price":1.0,"Checked":"2017-07-27T15:59:50.786215+01:00"},{"Supermarket":0,"Price":1.0,"Checked":"2017-07-28T13:32:54.525362+01:00"},{"Supermarket":0,"Price":1.0,"Checked":"2017-07-31T16:04:12.434087+01:00"},{"Supermarket":0,"Price":1.0,"Checked":"2017-08-07T09:23:15.181155+01:00"},{"Supermarket":0,"Price":1.0,"Checked":"2017-08-08T11:02:10.102459+01:00"}]}