{"EAN":"5000175410227","Name":"Batchelors Super Noodles Mild Curry 100G","TescoProductId":255447864,"TescoClientId":255447864,"TescoBaseProductId":50433886,"Image":"https://img.tesco.com/Groceries/pi/227/5000175410227/IDShot_110x110.jpg","TescoPermanentlyUnavailable":false,"PriceHistory":[{"Supermarket":0,"Price":0.81,"Checked":"2017-07-21T09:02:04.07853+01:00"},{"Supermarket":0,"Price":0.81,"Checked":"2017-07-24T12:43:24.314067+01:00"},{"Supermarket":0,"Price":0.81,"Checked":"2017-07-25T10:32:18.825639+01:00"},{"Supermarket":0,"Price":0.81,"Checked":"2017-07-26T10:44:32.630632+01:00"},{"Supermarket":0,"Price":0.81,"Checked":"2017-07-27T10:19:53.142057+01:00"},{"Supermarket":0,"Price":0.81,"Checked":"2017-07-28T13:34:35.261074+01:00"},{"Supermarket":0,"Price":0.81,"Checked":"2017-07-31T15:57:10.020223+01:00"}]}