{"EAN":"5010204060217","Name":"Tesco Minty Green Vegetables 250G","TescoProductId":256111494,"TescoClientId":256111494,"TescoBaseProductId":57940171,"Image":"https://img.tesco.com/Groceries/pi/217/5010204060217/IDShot_110x110.jpg","PriceHistory":[{"Supermarket":0,"Price":2.0,"Checked":"2017-07-24T13:06:08.804661+01:00"},{"Supermarket":0,"Price":2.0,"Checked":"2017-07-24T12:54:42.648306+01:00"},{"Supermarket":0,"Price":2.0,"Checked":"2017-07-24T12:54:42.40158+01:00"},{"Supermarket":0,"Price":2.0,"Checked":"2017-07-24T12:54:42.149286+01:00"},{"Supermarket":0,"Price":2.0,"Checked":"2017-07-24T12:54:41.876678+01:00"},{"Supermarket":0,"Price":2.0,"Checked":"2017-07-24T12:52:08.699595+01:00"},{"Supermarket":0,"Price":2.0,"Checked":"2017-07-24T12:51:57.371557+01:00"},{"Supermarket":0,"Price":2.0,"Checked":"2017-07-24T12:50:22.19694+01:00"},{"Supermarket":0,"Price":2.0,"Checked":"2017-07-24T12:47:30.616161+01:00"},{"Supermarket":0,"Price":2.0,"Checked":"2017-07-24T12:44:26.299515+01:00"},{"Supermarket":0,"Price":2.0,"Checked":"2017-07-24T12:44:04.771547+01:00"},{"Supermarket":0,"Price":2.0,"Checked":"2017-07-23T21:26:23.293299+01:00"},{"Supermarket":0,"Price":2.0,"Checked":"2017-07-23T21:03:15.472485+01:00"},{"Supermarket":0,"Price":2.0,"Checked":"2017-07-23T21:03:14.602672+01:00"},{"Supermarket":0,"Price":2.0,"Checked":"2017-07-23T21:03:13.80998+01:00"},{"Supermarket":0,"Price":2.0,"Checked":"2017-07-23T21:03:12.889268+01:00"},{"Supermarket":0,"Price":2.0,"Checked":"2017-07-23T20:57:29.659563+01:00"},{"Supermarket":0,"Price":2.0,"Checked":"2017-07-23T20:57:06.7224+01:00"},{"Supermarket":0,"Price":2.0,"Checked":"2017-07-23T20:53:32.608806+01:00"},{"Supermarket":0,"Price":2.0,"Checked":"2017-07-23T20:48:13.756853+01:00"},{"Supermarket":0,"Price":2.0,"Checked":"2017-07-23T20:42:00.77084+01:00"},{"Supermarket":0,"Price":2.0,"Checked":"2017-07-23T20:24:35.404559+01:00"},{"Supermarket":0,"Price":2.0,"Checked":"2017-07-21T09:03:51.32943+01:00"},{"Supermarket":0,"Price":2.0,"Checked":"2017-07-20T11:49:47.76734+01:00"},{"Supermarket":0,"Price":2.0,"Checked":"2017-07-20T11:52:26.204071+01:00"},{"Supermarket":0,"Price":2.0,"Checked":"2017-07-20T11:53:30.540194+01:00"},{"Supermarket":0,"Price":2.0,"Checked":"2017-07-20T11:53:40.014244+01:00"},{"Supermarket":0,"Price":2.0,"Checked":"2017-07-20T11:55:40.240529+01:00"},{"Supermarket":0,"Price":2.0,"Checked":"2017-07-20T11:55:41.218752+01:00"},{"Supermarket":0,"Price":2.0,"Checked":"2017-07-20T13:55:47.201093+01:00"},{"Supermarket":0,"Price":2.0,"Checked":"2017-07-20T13:55:58.112442+01:00"}]}