{"EAN":"0000050020140","Name":"Schwartz Ground Mixed Spice 28G Jar","TescoProductId":257512127,"TescoClientId":257512127,"TescoBaseProductId":50042444,"Image":"https://img.tesco.com/Groceries/pi/140/0000050020140/IDShot_110x110.jpg","TescoPermanentlyUnavailable":false,"PriceHistory":[{"Supermarket":0,"Price":1.5,"Checked":"2017-08-01T09:08:03.669566+01:00"},{"Supermarket":0,"Price":1.5,"Checked":"2017-08-02T09:16:26.917664+01:00"},{"Supermarket":0,"Price":1.5,"Checked":"2017-08-03T09:32:03.27567+01:00"},{"Supermarket":0,"Price":1.5,"Checked":"2017-08-04T09:43:31.855672+01:00"},{"Supermarket":0,"Price":1.5,"Checked":"2017-08-07T09:13:00.819532+01:00"},{"Supermarket":0,"Price":1.5,"Checked":"2017-08-08T10:51:32.154428+01:00"}]}