{"EAN":"5051008250923","Name":"Tesco Klipfresh Foodsaver 3.4L","TescoProductId":257824484,"TescoClientId":257824484,"TescoBaseProductId":53862768,"Image":"https://img.tesco.com/Groceries/pi/923/5051008250923/IDShot_110x110.jpg","TescoPermanentlyUnavailable":false,"PriceHistory":[{"Supermarket":0,"Price":4.75,"Checked":"2017-08-01T09:08:40.335594+01:00"},{"Supermarket":0,"Price":4.75,"Checked":"2017-08-02T09:47:32.081487+01:00"},{"Supermarket":0,"Price":4.75,"Checked":"2017-08-03T09:19:53.883663+01:00"}]}