{"EAN":"5000147030262","Name":"Robinsons Orange And Mango No Added Sugar 1L","TescoProductId":258043473,"TescoClientId":258043473,"TescoBaseProductId":51576513,"Image":"https://img.tesco.com/Groceries/pi/262/5000147030262/IDShot_110x110.jpg","TescoPermanentlyUnavailable":false,"PriceHistory":[{"Supermarket":0,"Price":1.49,"Checked":"2017-07-17T16:13:17.873931+01:00"},{"Supermarket":0,"Price":1.49,"Checked":"2017-07-20T17:14:12.267261+01:00"},{"Supermarket":0,"Price":1.49,"Checked":"2017-07-21T14:45:15.532714+01:00"},{"Supermarket":0,"Price":1.49,"Checked":"2017-07-24T12:47:04.924692+01:00"},{"Supermarket":0,"Price":1.49,"Checked":"2017-07-25T10:35:37.626712+01:00"},{"Supermarket":0,"Price":1.49,"Checked":"2017-07-26T10:50:17.650096+01:00"},{"Supermarket":0,"Price":1.49,"Checked":"2017-07-27T16:00:32.904787+01:00"},{"Supermarket":0,"Price":1.49,"Checked":"2017-07-28T13:41:19.066503+01:00"},{"Supermarket":0,"Price":1.49,"Checked":"2017-08-01T09:09:05.514964+01:00"},{"Supermarket":0,"Price":1.49,"Checked":"2017-08-02T09:19:29.414407+01:00"},{"Supermarket":0,"Price":1.49,"Checked":"2017-08-03T09:13:50.24269+01:00"},{"Supermarket":0,"Price":1.49,"Checked":"2017-08-04T09:48:16.893603+01:00"},{"Supermarket":0,"Price":1.49,"Checked":"2017-08-07T08:57:54.115699+01:00"},{"Supermarket":0,"Price":1.49,"Checked":"2017-08-08T15:00:24.844676+01:00"},{"Supermarket":0,"Price":1.49,"Checked":"2017-08-09T12:54:00.168328+01:00"},{"Supermarket":0,"Price":1.49,"Checked":"2017-08-10T10:19:44.001515+01:00"}]}