{"EAN":"5051140208363","Name":"Tesco Finest Royal Korma 350G","TescoProductId":260361197,"TescoClientId":260361197,"TescoBaseProductId":57806671,"Image":"https://img.tesco.com/Groceries/pi/363/5051140208363/IDShot_110x110.jpg","TescoPermanentlyUnavailable":false,"PriceHistory":[{"Supermarket":0,"Price":1.99,"Checked":"2017-08-01T09:13:10.133997+01:00"},{"Supermarket":0,"Price":1.99,"Checked":"2017-08-02T09:32:53.129995+01:00"},{"Supermarket":0,"Price":1.99,"Checked":"2017-08-03T09:07:55.995334+01:00"},{"Supermarket":0,"Price":1.99,"Checked":"2017-08-04T10:04:16.312047+01:00"},{"Supermarket":0,"Price":1.99,"Checked":"2017-08-07T09:11:29.841792+01:00"}]}