{"EAN":"8008440122216","Name":"Peroni Nastro Azzurro 12X330ml","TescoProductId":262407821,"TescoClientId":262407821,"TescoBaseProductId":61158158,"Image":"https://img.tesco.com/Groceries/pi/216/8008440122216/IDShot_110x110.jpg","TescoPermanentlyUnavailable":false,"PriceHistory":[{"Supermarket":0,"Price":14.0,"Checked":"2017-07-17T16:13:23.652822+01:00"},{"Supermarket":0,"Price":14.0,"Checked":"2017-07-20T17:14:26.506032+01:00"},{"Supermarket":0,"Price":14.0,"Checked":"2017-07-21T14:45:34.766278+01:00"},{"Supermarket":0,"Price":14.0,"Checked":"2017-07-24T12:51:38.395443+01:00"},{"Supermarket":0,"Price":14.0,"Checked":"2017-07-25T10:40:03.832808+01:00"},{"Supermarket":0,"Price":14.0,"Checked":"2017-07-26T10:58:11.262967+01:00"},{"Supermarket":0,"Price":14.0,"Checked":"2017-07-27T16:05:02.162295+01:00"},{"Supermarket":0,"Price":14.0,"Checked":"2017-07-28T13:50:30.584695+01:00"},{"Supermarket":0,"Price":14.0,"Checked":"2017-08-01T09:16:26.179426+01:00"},{"Supermarket":0,"Price":14.0,"Checked":"2017-08-02T09:51:14.41216+01:00"},{"Supermarket":0,"Price":14.0,"Checked":"2017-08-03T09:57:13.308344+01:00"},{"Supermarket":0,"Price":14.0,"Checked":"2017-08-04T10:34:26.843695+01:00"},{"Supermarket":0,"Price":16.5,"Checked":"2017-08-07T09:37:09.473449+01:00"},{"Supermarket":0,"Price":16.5,"Checked":"2017-08-08T11:11:26.330482+01:00"}]}