{"EAN":"4891028664994","Name":"Vitasoy Soya Drink 250Ml","TescoProductId":263414766,"TescoClientId":263414766,"TescoBaseProductId":62139548,"Image":"https://img.tesco.com/Groceries/pi/994/4891028664994/IDShot_110x110.jpg","TescoPermanentlyUnavailable":false,"PriceHistory":[{"Supermarket":0,"Price":2.42,"Checked":"2017-08-01T09:17:53.45458+01:00"},{"Supermarket":0,"Price":2.42,"Checked":"2017-08-04T10:11:39.133153+01:00"},{"Supermarket":0,"Price":2.42,"Checked":"2017-08-07T09:38:23.960913+01:00"},{"Supermarket":0,"Price":2.42,"Checked":"2017-08-08T11:12:15.946273+01:00"},{"Supermarket":0,"Price":2.42,"Checked":"2017-08-09T13:18:26.015927+01:00"},{"Supermarket":0,"Price":2.42,"Checked":"2017-08-10T10:48:05.944734+01:00"}]}