{"EAN":"7804320328164","Name":"Cyt Late Harvest Sauvignon Blanc 37.5Cl","TescoProductId":266232976,"TescoClientId":266232976,"TescoBaseProductId":65549202,"Image":"https://img.tesco.com/Groceries/pi/164/7804320328164/IDShot_110x110.jpg","TescoPermanentlyUnavailable":false,"PriceHistory":[{"Supermarket":0,"Price":5.0,"Checked":"2017-08-01T09:23:07.645384+01:00"},{"Supermarket":0,"Price":5.0,"Checked":"2017-08-02T09:36:43.800965+01:00"},{"Supermarket":0,"Price":5.0,"Checked":"2017-08-03T09:36:15.367068+01:00"},{"Supermarket":0,"Price":5.0,"Checked":"2017-08-04T10:10:12.51156+01:00"},{"Supermarket":0,"Price":7.5,"Checked":"2017-08-07T09:15:53.061021+01:00"},{"Supermarket":0,"Price":7.5,"Checked":"2017-08-08T15:47:58.792916+01:00"},{"Supermarket":0,"Price":7.5,"Checked":"2017-08-09T13:33:41.041457+01:00"},{"Supermarket":0,"Price":7.5,"Checked":"2017-08-10T11:01:52.342328+01:00"}]}