{"EAN":"5060113070807","Name":"Cadbury Chocolate Fresh Cream Cake 430G","TescoProductId":266372981,"TescoClientId":266372981,"TescoBaseProductId":65683710,"Image":"https://img.tesco.com/Groceries/pi/807/5060113070807/IDShot_110x110.jpg","TescoPermanentlyUnavailable":false,"PriceHistory":[{"Supermarket":0,"Price":2.0,"Checked":"2017-08-01T09:23:23.858829+01:00"},{"Supermarket":0,"Price":2.0,"Checked":"2017-08-02T09:28:38.352785+01:00"},{"Supermarket":0,"Price":2.0,"Checked":"2017-08-03T10:02:09.839765+01:00"},{"Supermarket":0,"Price":2.0,"Checked":"2017-08-04T09:59:36.40416+01:00"},{"Supermarket":0,"Price":2.0,"Checked":"2017-08-07T09:06:53.408339+01:00"},{"Supermarket":0,"Price":2.0,"Checked":"2017-08-08T14:55:01.215184+01:00"},{"Supermarket":0,"Price":2.0,"Checked":"2017-08-09T13:34:29.931527+01:00"}]}