{"EAN":"7804320131344","Name":"Casillero Del Diablo Shiraz Rose 75Cl","TescoProductId":266434386,"TescoClientId":266434386,"TescoBaseProductId":65742641,"Image":"https://img.tesco.com/Groceries/pi/344/7804320131344/IDShot_110x110.jpg","TescoPermanentlyUnavailable":false,"PriceHistory":[{"Supermarket":0,"Price":8.5,"Checked":"2017-07-17T16:14:09.807443+01:00"},{"Supermarket":0,"Price":8.5,"Checked":"2017-07-20T17:10:26.12379+01:00"},{"Supermarket":0,"Price":8.5,"Checked":"2017-07-21T14:41:58.283021+01:00"},{"Supermarket":0,"Price":8.5,"Checked":"2017-07-24T12:56:04.33531+01:00"},{"Supermarket":0,"Price":8.5,"Checked":"2017-07-25T10:44:26.860739+01:00"},{"Supermarket":0,"Price":8.5,"Checked":"2017-07-26T11:05:33.847337+01:00"},{"Supermarket":0,"Price":8.5,"Checked":"2017-07-27T10:40:29.396981+01:00"},{"Supermarket":0,"Price":8.5,"Checked":"2017-08-01T09:23:40.619806+01:00"},{"Supermarket":0,"Price":8.5,"Checked":"2017-08-02T09:54:21.043651+01:00"}]}