{"EAN":"5000394504424","Name":"Duracell Speciality Lr44 2 Pack","TescoProductId":267504646,"TescoClientId":267504646,"TescoBaseProductId":66783607,"Image":"https://img.tesco.com/Groceries/pi/424/5000394504424/IDShot_110x110.jpg","TescoPermanentlyUnavailable":false,"PriceHistory":[{"Supermarket":0,"Price":5.0,"Checked":"2017-08-08T14:12:47.757733+01:00"},{"Supermarket":0,"Price":5.0,"Checked":"2017-08-09T13:42:34.47196+01:00"},{"Supermarket":0,"Price":5.0,"Checked":"2017-08-10T11:09:55.711368+01:00"}]}