{"EAN":"8718114885094","Name":"Colman's Season & Shake Mediterranean Chicken Southern Mix 33G","TescoProductId":267678543,"TescoClientId":267678543,"TescoBaseProductId":66952621,"Image":"https://img.tesco.com/Groceries/pi/094/8718114885094/IDShot_110x110.jpg","TescoPermanentlyUnavailable":false,"PriceHistory":[{"Supermarket":0,"Price":1.0,"Checked":"2017-08-01T09:26:05.701261+01:00"},{"Supermarket":0,"Price":1.0,"Checked":"2017-08-02T09:29:57.242196+01:00"},{"Supermarket":0,"Price":1.0,"Checked":"2017-08-03T09:26:51.801239+01:00"},{"Supermarket":0,"Price":1.0,"Checked":"2017-08-04T10:01:26.8668+01:00"},{"Supermarket":0,"Price":1.0,"Checked":"2017-08-07T08:51:51.245354+01:00"},{"Supermarket":0,"Price":1.0,"Checked":"2017-08-08T14:23:45.849427+01:00"},{"Supermarket":0,"Price":1.0,"Checked":"2017-08-09T13:43:33.721531+01:00"}]}