{"EAN":"8711000279472","Name":"Douwe Egberts Pure Gold Instant Coffee 190G","TescoProductId":271183270,"TescoClientId":271183270,"TescoBaseProductId":51453060,"Image":"https://img.tesco.com/Groceries/pi/472/8711000279472/IDShot_110x110.jpg","TescoPermanentlyUnavailable":false,"PriceHistory":[{"Supermarket":0,"Price":5.0,"Checked":"2017-07-20T17:14:23.606143+01:00"},{"Supermarket":0,"Price":5.0,"Checked":"2017-07-21T14:45:31.255893+01:00"},{"Supermarket":0,"Price":5.0,"Checked":"2017-07-24T12:59:27.913134+01:00"},{"Supermarket":0,"Price":5.0,"Checked":"2017-07-25T10:47:41.616711+01:00"},{"Supermarket":0,"Price":5.0,"Checked":"2017-07-26T11:11:41.17252+01:00"},{"Supermarket":0,"Price":5.0,"Checked":"2017-07-27T16:00:39.922698+01:00"},{"Supermarket":0,"Price":5.0,"Checked":"2017-07-28T14:05:59.78711+01:00"},{"Supermarket":0,"Price":5.0,"Checked":"2017-07-31T16:12:15.978405+01:00"},{"Supermarket":0,"Price":6.29,"Checked":"2017-08-01T09:34:01.344509+01:00"},{"Supermarket":0,"Price":6.29,"Checked":"2017-08-02T09:56:55.828502+01:00"}]}