{"EAN":"3600522021605","Name":"L’Oreal Men Expert Vita Lift 5 Moisturiser 50Ml","TescoProductId":271317015,"TescoClientId":271317015,"TescoBaseProductId":70651326,"Image":"https://img.tesco.com/Groceries/pi/605/3600522021605/IDShot_110x110.jpg","TescoPermanentlyUnavailable":false,"PriceHistory":[{"Supermarket":0,"Price":10.0,"Checked":"2017-08-01T09:34:44.234642+01:00"},{"Supermarket":0,"Price":10.0,"Checked":"2017-08-02T09:18:55.326074+01:00"},{"Supermarket":0,"Price":10.0,"Checked":"2017-08-03T09:13:09.527749+01:00"},{"Supermarket":0,"Price":10.0,"Checked":"2017-08-04T09:47:33.853963+01:00"},{"Supermarket":0,"Price":10.0,"Checked":"2017-08-07T08:57:23.573187+01:00"}]}