{"EAN":"5391518270074","Name":"Banana Boat Baby Sun Protect Lotion Spf 50 60Ml","TescoProductId":271912290,"TescoClientId":271912290,"TescoBaseProductId":70944441,"Image":"https://img.tesco.com/Groceries/pi/074/5391518270074/IDShot_110x110.jpg","TescoPermanentlyUnavailable":false,"PriceHistory":[{"Supermarket":0,"Price":3.0,"Checked":"2017-07-17T16:13:54.943761+01:00"},{"Supermarket":0,"Price":3.0,"Checked":"2017-07-20T17:16:51.057764+01:00"},{"Supermarket":0,"Price":3.0,"Checked":"2017-07-21T14:48:14.895535+01:00"},{"Supermarket":0,"Price":3.0,"Checked":"2017-07-24T13:00:24.941778+01:00"},{"Supermarket":0,"Price":3.0,"Checked":"2017-07-25T10:48:35.443572+01:00"},{"Supermarket":0,"Price":3.0,"Checked":"2017-07-26T11:13:25.662599+01:00"},{"Supermarket":0,"Price":3.0,"Checked":"2017-07-27T16:02:08.833878+01:00"},{"Supermarket":0,"Price":3.0,"Checked":"2017-07-28T14:07:49.190784+01:00"},{"Supermarket":0,"Price":3.0,"Checked":"2017-08-01T09:37:19.011236+01:00"},{"Supermarket":0,"Price":3.0,"Checked":"2017-08-02T09:57:50.620319+01:00"},{"Supermarket":0,"Price":3.0,"Checked":"2017-08-03T10:07:23.98486+01:00"}]}