{"EAN":"4084500616233","Name":"Fairy Non Bio. Pods Washing Capsules 38 Washes","TescoProductId":271910073,"TescoClientId":271910073,"TescoBaseProductId":70943505,"Image":"https://img.tesco.com/Groceries/pi/233/4084500616233/IDShot_110x110.jpg","PriceHistory":[{"Supermarket":0,"Price":9.0,"Checked":"2017-07-24T13:00:24.400832+01:00"},{"Supermarket":0,"Price":9.0,"Checked":"2017-07-23T21:15:18.818207+01:00"},{"Supermarket":0,"Price":9.0,"Checked":"2017-07-21T14:46:00.965821+01:00"},{"Supermarket":0,"Price":9.0,"Checked":"2017-07-17T10:42:44.959683+01:00"},{"Supermarket":0,"Price":9.0,"Checked":"2017-07-17T11:17:37.605329+01:00"},{"Supermarket":0,"Price":9.0,"Checked":"2017-07-17T16:13:51.848107+01:00"},{"Supermarket":0,"Price":9.0,"Checked":"2017-07-20T11:59:29.71609+01:00"},{"Supermarket":0,"Price":9.0,"Checked":"2017-07-20T15:20:02.7605+01:00"},{"Supermarket":0,"Price":9.0,"Checked":"2017-07-20T15:20:35.78076+01:00"},{"Supermarket":0,"Price":9.0,"Checked":"2017-07-20T17:14:52.452235+01:00"}]}