{"EAN":"5411188110835","Name":"Alpro Almond Longlife Milk Alternative 1 Litre","TescoProductId":272012512,"TescoClientId":272012512,"TescoBaseProductId":70987983,"Image":"https://img.tesco.com/Groceries/pi/835/5411188110835/IDShot_110x110.jpg","TescoPermanentlyUnavailable":false,"PriceHistory":[{"Supermarket":0,"Price":1.7,"Checked":"2017-08-01T09:37:30.307481+01:00"},{"Supermarket":0,"Price":1.7,"Checked":"2017-08-02T09:27:54.893312+01:00"},{"Supermarket":0,"Price":1.7,"Checked":"2017-08-03T09:24:48.084324+01:00"},{"Supermarket":0,"Price":1.7,"Checked":"2017-08-04T09:59:03.072339+01:00"},{"Supermarket":0,"Price":1.7,"Checked":"2017-08-07T09:06:35.9721+01:00"}]}