{"EAN":"5000119090645","Name":"Tesco Pickled Sliced Beetroot 710G","TescoProductId":272309421,"TescoClientId":272309421,"TescoBaseProductId":50321765,"Image":"https://img.tesco.com/Groceries/pi/645/5000119090645/IDShot_110x110.jpg","TescoPermanentlyUnavailable":false,"PriceHistory":[{"Supermarket":0,"Price":1.1,"Checked":"2017-07-17T16:12:40.090247+01:00"},{"Supermarket":0,"Price":1.1,"Checked":"2017-07-20T17:13:18.951772+01:00"},{"Supermarket":0,"Price":1.1,"Checked":"2017-07-21T14:44:16.637818+01:00"},{"Supermarket":0,"Price":1.1,"Checked":"2017-07-24T13:00:44.320148+01:00"},{"Supermarket":0,"Price":1.1,"Checked":"2017-07-25T10:49:04.568279+01:00"},{"Supermarket":0,"Price":1.1,"Checked":"2017-07-26T11:14:01.912888+01:00"},{"Supermarket":0,"Price":1.1,"Checked":"2017-07-27T16:00:04.520477+01:00"},{"Supermarket":0,"Price":1.1,"Checked":"2017-07-28T14:08:26.562994+01:00"},{"Supermarket":0,"Price":1.1,"Checked":"2017-08-01T09:38:28.254735+01:00"},{"Supermarket":0,"Price":1.1,"Checked":"2017-08-02T09:25:58.4227+01:00"},{"Supermarket":0,"Price":1.1,"Checked":"2017-08-03T09:22:33.93863+01:00"},{"Supermarket":0,"Price":1.1,"Checked":"2017-08-04T09:56:48.58586+01:00"},{"Supermarket":0,"Price":1.1,"Checked":"2017-08-07T09:04:51.295147+01:00"},{"Supermarket":0,"Price":1.1,"Checked":"2017-08-08T14:58:05.123449+01:00"},{"Supermarket":0,"Price":1.1,"Checked":"2017-08-09T14:01:28.766322+01:00"},{"Supermarket":0,"Price":1.1,"Checked":"2017-08-10T11:30:16.39936+01:00"}]}