{"EAN":"5018735224924","Name":"Soreen Malt Lunchbox Loaves 5 Pack","TescoProductId":273421003,"TescoClientId":273421003,"TescoBaseProductId":71666739,"Image":"https://img.tesco.com/Groceries/pi/924/5018735224924/IDShot_110x110.jpg","TescoPermanentlyUnavailable":false,"PriceHistory":[{"Supermarket":0,"Price":1.35,"Checked":"2017-07-17T16:12:28.879503+01:00"},{"Supermarket":0,"Price":1.35,"Checked":"2017-07-20T17:12:50.939955+01:00"},{"Supermarket":0,"Price":1.35,"Checked":"2017-07-21T14:53:28.886154+01:00"},{"Supermarket":0,"Price":1.35,"Checked":"2017-07-24T13:01:56.846698+01:00"},{"Supermarket":0,"Price":1.35,"Checked":"2017-07-25T10:50:07.017748+01:00"},{"Supermarket":0,"Price":1.35,"Checked":"2017-07-26T11:16:05.4575+01:00"},{"Supermarket":0,"Price":1.35,"Checked":"2017-07-27T15:59:42.833064+01:00"},{"Supermarket":0,"Price":1.35,"Checked":"2017-07-28T14:10:51.75591+01:00"},{"Supermarket":0,"Price":1.35,"Checked":"2017-08-01T09:42:09.967855+01:00"}]}