{"EAN":"5052909509691","Name":"Bella Cucina Prosecco 75Cl","TescoProductId":273782335,"TescoClientId":273782335,"TescoBaseProductId":71846302,"Image":"https://img.tesco.com/Groceries/pi/691/5052909509691/IDShot_110x110.jpg","TescoPermanentlyUnavailable":false,"PriceHistory":[{"Supermarket":0,"Price":5.85,"Checked":"2017-07-17T16:13:23.754272+01:00"},{"Supermarket":0,"Price":5.85,"Checked":"2017-07-20T17:14:25.342968+01:00"},{"Supermarket":0,"Price":5.85,"Checked":"2017-07-21T14:45:33.603612+01:00"},{"Supermarket":0,"Price":5.85,"Checked":"2017-07-24T13:02:21.151045+01:00"},{"Supermarket":0,"Price":5.85,"Checked":"2017-07-25T10:50:25.098366+01:00"},{"Supermarket":0,"Price":5.85,"Checked":"2017-07-26T11:16:40.078928+01:00"},{"Supermarket":0,"Price":5.85,"Checked":"2017-07-27T16:00:41.039611+01:00"},{"Supermarket":0,"Price":5.85,"Checked":"2017-07-28T14:11:31.579141+01:00"},{"Supermarket":0,"Price":5.85,"Checked":"2017-08-01T09:43:09.159472+01:00"},{"Supermarket":0,"Price":5.85,"Checked":"2017-08-02T09:17:50.979419+01:00"},{"Supermarket":0,"Price":5.85,"Checked":"2017-08-03T09:35:38.964246+01:00"},{"Supermarket":0,"Price":5.85,"Checked":"2017-08-04T10:09:38.076948+01:00"},{"Supermarket":0,"Price":5.85,"Checked":"2017-08-07T09:15:25.418742+01:00"},{"Supermarket":0,"Price":5.85,"Checked":"2017-08-08T10:53:37.707344+01:00"}]}