{"EAN":"5052909625346","Name":"Tesco Wholefoods Pumpkin Seeds 250G","TescoProductId":273812128,"TescoClientId":273812128,"TescoBaseProductId":71875134,"Image":"https://img.tesco.com/Groceries/pi/346/5052909625346/IDShot_110x110.jpg","TescoPermanentlyUnavailable":false,"PriceHistory":[{"Supermarket":0,"Price":2.2,"Checked":"2017-08-01T09:43:23.721714+01:00"},{"Supermarket":0,"Price":2.2,"Checked":"2017-08-02T09:28:40.780333+01:00"},{"Supermarket":0,"Price":2.2,"Checked":"2017-08-03T09:25:38.316915+01:00"},{"Supermarket":0,"Price":2.2,"Checked":"2017-08-04T10:00:06.924811+01:00"}]}