{"EAN":"7501064193101","Name":"Corona Extra 4X330ml","TescoProductId":274347579,"TescoClientId":274347579,"TescoBaseProductId":51373238,"Image":"https://img.tesco.com/Groceries/pi/101/7501064193101/IDShot_110x110.jpg","TescoPermanentlyUnavailable":false,"PriceHistory":[{"Supermarket":0,"Price":5.1,"Checked":"2017-07-28T14:12:41.135161+01:00"},{"Supermarket":0,"Price":5.1,"Checked":"2017-07-27T16:05:02.162295+01:00"},{"Supermarket":0,"Price":5.1,"Checked":"2017-07-27T16:03:10.994037+01:00"},{"Supermarket":0,"Price":5.1,"Checked":"2017-07-27T16:03:08.951708+01:00"},{"Supermarket":0,"Price":5.1,"Checked":"2017-07-27T16:03:07.680101+01:00"},{"Supermarket":0,"Price":5.1,"Checked":"2017-07-27T15:56:36.274962+01:00"}]}