{"EAN":"5055257886520","Name":"Golden Sunrise Noodle Bowls 2 X 70G","TescoProductId":274840916,"TescoClientId":274840916,"TescoBaseProductId":72388859,"Image":"https://img.tesco.com/Groceries/pi/520/5055257886520/IDShot_110x110.jpg","TescoPermanentlyUnavailable":false,"PriceHistory":[{"Supermarket":0,"Price":1.0,"Checked":"2017-08-01T09:47:18.62879+01:00"},{"Supermarket":0,"Price":1.0,"Checked":"2017-08-02T09:37:42.172552+01:00"},{"Supermarket":0,"Price":1.0,"Checked":"2017-08-03T09:37:49.178606+01:00"},{"Supermarket":0,"Price":1.0,"Checked":"2017-08-07T09:17:12.542861+01:00"},{"Supermarket":0,"Price":1.0,"Checked":"2017-08-08T10:55:20.490401+01:00"}]}