{"EAN":"5053947102271","Name":"Tesco Finest Frozen Jumbo Raw King Prawns 240G","TescoProductId":277744283,"TescoClientId":277744283,"TescoBaseProductId":66784176,"Image":"https://img.tesco.com/Groceries/pi/271/5053947102271/IDShot_110x110.jpg","TescoPermanentlyUnavailable":false,"PriceHistory":[{"Supermarket":0,"Price":4.5,"Checked":"2017-07-17T16:12:49.258426+01:00"},{"Supermarket":0,"Price":4.5,"Checked":"2017-07-20T17:13:54.489659+01:00"},{"Supermarket":0,"Price":4.5,"Checked":"2017-07-23T21:26:52.474559+01:00"},{"Supermarket":0,"Price":3.5,"Checked":"2017-07-24T13:06:21.899497+01:00"},{"Supermarket":0,"Price":3.5,"Checked":"2017-07-25T10:53:55.904266+01:00"},{"Supermarket":0,"Price":3.5,"Checked":"2017-07-26T11:22:58.723362+01:00"},{"Supermarket":0,"Price":3.5,"Checked":"2017-07-27T10:56:52.159621+01:00"},{"Supermarket":0,"Price":3.5,"Checked":"2017-07-28T14:18:34.695655+01:00"}]}