{"EAN":"0000003234433","Name":"Tesco Root Vegetable For Mashing 720G","TescoProductId":277972334,"TescoClientId":277972334,"TescoBaseProductId":63866244,"Image":"https://img.tesco.com/Groceries/pi/433/0000003234433/IDShot_110x110.jpg","TescoPermanentlyUnavailable":false,"PriceHistory":[{"Supermarket":0,"Price":0.85,"Checked":"2017-07-31T15:57:25.186048+01:00"},{"Supermarket":0,"Price":0.85,"Checked":"2017-08-01T10:34:53.272733+01:00"},{"Supermarket":0,"Price":0.85,"Checked":"2017-08-02T10:08:52.879974+01:00"},{"Supermarket":0,"Price":0.85,"Checked":"2017-08-03T09:03:04.172095+01:00"},{"Supermarket":0,"Price":0.85,"Checked":"2017-08-04T09:37:23.705269+01:00"}]}