{"EAN":"5000328329321","Name":"Walkers Quavers Cheese Snacks 6 X 16 G","TescoProductId":278416273,"TescoClientId":278416273,"TescoBaseProductId":50390912,"Image":"https://img.tesco.com/Groceries/pi/321/5000328329321/IDShot_110x110.jpg","PriceHistory":[{"Supermarket":0,"Price":1.5,"Checked":"2017-07-24T13:06:48.504921+01:00"},{"Supermarket":0,"Price":1.5,"Checked":"2017-07-23T21:28:02.653382+01:00"},{"Supermarket":0,"Price":1.5,"Checked":"2017-07-21T14:44:19.091261+01:00"},{"Supermarket":0,"Price":1.5,"Checked":"2017-07-21T14:44:01.881335+01:00"},{"Supermarket":0,"Price":1.5,"Checked":"2017-07-21T14:40:45.333598+01:00"},{"Supermarket":0,"Price":1.5,"Checked":"2017-07-17T10:42:35.043112+01:00"},{"Supermarket":0,"Price":1.5,"Checked":"2017-07-17T10:42:38.316699+01:00"},{"Supermarket":0,"Price":1.5,"Checked":"2017-07-17T11:17:27.468716+01:00"},{"Supermarket":0,"Price":1.5,"Checked":"2017-07-17T11:17:30.563128+01:00"},{"Supermarket":0,"Price":1.5,"Checked":"2017-07-17T16:11:46.05807+01:00"},{"Supermarket":0,"Price":1.5,"Checked":"2017-07-17T16:12:36.763968+01:00"},{"Supermarket":0,"Price":1.5,"Checked":"2017-07-17T16:12:40.158952+01:00"},{"Supermarket":0,"Price":1.5,"Checked":"2017-07-17T16:12:43.290713+01:00"},{"Supermarket":0,"Price":1.5,"Checked":"2017-07-20T12:03:04.768275+01:00"},{"Supermarket":0,"Price":1.5,"Checked":"2017-07-20T15:19:10.623467+01:00"},{"Supermarket":0,"Price":1.5,"Checked":"2017-07-20T15:19:18.68219+01:00"},{"Supermarket":0,"Price":1.5,"Checked":"2017-07-20T17:13:03.444853+01:00"},{"Supermarket":0,"Price":1.5,"Checked":"2017-07-20T17:13:21.381308+01:00"}]}