{"EAN":"5053947608469","Name":"Tesco Finest British Mint Sauce 180G","TescoProductId":279233055,"TescoClientId":279233055,"TescoBaseProductId":74472140,"Image":"https://img.tesco.com/Groceries/pi/469/5053947608469/IDShot_110x110.jpg","TescoPermanentlyUnavailable":false,"PriceHistory":[{"Supermarket":0,"Price":1.49,"Checked":"2017-08-01T10:01:29.166477+01:00"},{"Supermarket":0,"Price":1.49,"Checked":"2017-08-02T09:31:57.4455+01:00"},{"Supermarket":0,"Price":1.49,"Checked":"2017-08-03T09:07:11.081019+01:00"},{"Supermarket":0,"Price":1.49,"Checked":"2017-08-04T09:41:32.104899+01:00"},{"Supermarket":0,"Price":1.49,"Checked":"2017-08-07T08:52:56.316967+01:00"},{"Supermarket":0,"Price":1.49,"Checked":"2017-08-08T15:48:10.558195+01:00"}]}