{"EAN":"4015600756956","Name":"Nice'n Easy Permanent Light Champagne Blonde 9Cb Hair Dye","TescoProductId":280380028,"TescoClientId":280380028,"TescoBaseProductId":75020668,"Image":"https://img.tesco.com/Groceries/pi/956/4015600756956/IDShot_110x110.jpg","TescoPermanentlyUnavailable":false,"PriceHistory":[{"Supermarket":0,"Price":6.0,"Checked":"2017-08-01T10:04:47.238533+01:00"},{"Supermarket":0,"Price":6.0,"Checked":"2017-08-02T09:24:31.66337+01:00"},{"Supermarket":0,"Price":6.0,"Checked":"2017-08-03T09:36:33.417877+01:00"},{"Supermarket":0,"Price":6.0,"Checked":"2017-08-04T10:10:30.203924+01:00"},{"Supermarket":0,"Price":6.0,"Checked":"2017-08-07T09:03:13.477793+01:00"},{"Supermarket":0,"Price":6.0,"Checked":"2017-08-08T13:47:17.684378+01:00"},{"Supermarket":0,"Price":6.0,"Checked":"2017-08-09T14:33:45.420463+01:00"}]}