{"EAN":"5060199680600","Name":"English Malt Whiskey Classic Black 70Cl","TescoProductId":280302975,"TescoClientId":280302975,"TescoBaseProductId":74952091,"Image":"https://img.tesco.com/Groceries/pi/600/5060199680600/IDShot_110x110.jpg","TescoPermanentlyUnavailable":false,"PriceHistory":[{"Supermarket":0,"Price":35.0,"Checked":"2017-08-01T10:04:30.907892+01:00"},{"Supermarket":0,"Price":35.0,"Checked":"2017-08-03T09:34:40.437489+01:00"},{"Supermarket":0,"Price":35.0,"Checked":"2017-08-04T10:09:21.747653+01:00"},{"Supermarket":0,"Price":35.0,"Checked":"2017-08-07T09:57:10.041378+01:00"},{"Supermarket":0,"Price":35.0,"Checked":"2017-08-09T14:33:24.562273+01:00"}]}