{"EAN":"5900562487002","Name":"Sokolow French Kabanos 120G","TescoProductId":282443234,"TescoClientId":282443234,"TescoBaseProductId":76038254,"Image":"https://img.tesco.com/Groceries/pi/002/5900562487002/IDShot_110x110.jpg","TescoPermanentlyUnavailable":false,"PriceHistory":[{"Supermarket":0,"Price":2.0,"Checked":"2017-08-01T10:10:18.954118+01:00"},{"Supermarket":0,"Price":2.0,"Checked":"2017-08-02T09:35:15.967346+01:00"},{"Supermarket":0,"Price":2.0,"Checked":"2017-08-03T09:34:03.231235+01:00"},{"Supermarket":0,"Price":2.0,"Checked":"2017-08-04T10:07:07.197428+01:00"},{"Supermarket":0,"Price":2.0,"Checked":"2017-08-07T09:14:15.8488+01:00"},{"Supermarket":0,"Price":2.0,"Checked":"2017-08-08T10:52:27.702549+01:00"}]}