{"EAN":"7613034753854","Name":"Bakers Allsorts Pack 98G","TescoProductId":284355934,"TescoClientId":284355934,"TescoBaseProductId":61300946,"Image":"https://img.tesco.com/Groceries/pi/854/7613034753854/IDShot_110x110.jpg","TescoPermanentlyUnavailable":false,"PriceHistory":[{"Supermarket":0,"Price":1.0,"Checked":"2017-07-20T12:03:05.261763+01:00"},{"Supermarket":0,"Price":1.0,"Checked":"2017-07-21T09:08:46.83812+01:00"},{"Supermarket":0,"Price":1.0,"Checked":"2017-07-24T13:11:51.109841+01:00"},{"Supermarket":0,"Price":1.0,"Checked":"2017-07-25T10:58:28.111638+01:00"},{"Supermarket":0,"Price":1.0,"Checked":"2017-07-26T11:31:44.632618+01:00"},{"Supermarket":0,"Price":1.0,"Checked":"2017-07-27T11:05:02.090951+01:00"},{"Supermarket":0,"Price":1.0,"Checked":"2017-07-28T14:25:25.574479+01:00"},{"Supermarket":0,"Price":1.0,"Checked":"2017-08-01T10:16:41.448631+01:00"},{"Supermarket":0,"Price":1.0,"Checked":"2017-08-04T10:59:22.833067+01:00"},{"Supermarket":0,"Price":1.0,"Checked":"2017-08-07T10:01:45.666794+01:00"},{"Supermarket":0,"Price":1.0,"Checked":"2017-08-08T14:28:45.545719+01:00"},{"Supermarket":0,"Price":1.0,"Checked":"2017-08-09T14:49:23.369075+01:00"}]}