{"EAN":null,"Name":"All Butter Croissant 2 Pack","TescoProductId":286519456,"TescoClientId":286519456,"TescoBaseProductId":78101171,"Image":null,"TescoPermanentlyUnavailable":false,"PriceHistory":[{"Supermarket":0,"Price":1.05,"Checked":"2017-07-17T16:12:28.563514+01:00"},{"Supermarket":0,"Price":1.05,"Checked":"2017-07-24T13:14:26.696857+01:00"},{"Supermarket":0,"Price":1.05,"Checked":"2017-07-25T11:00:45.115915+01:00"},{"Supermarket":0,"Price":1.05,"Checked":"2017-07-26T11:35:46.486415+01:00"},{"Supermarket":0,"Price":1.05,"Checked":"2017-07-27T15:59:42.342489+01:00"},{"Supermarket":0,"Price":1.05,"Checked":"2017-07-28T14:28:07.927737+01:00"}]}