{"EAN":"5054402551320","Name":"Tesco Cat's Choice Country Recipes Cat Pouches 12 X85g","TescoProductId":286747531,"TescoClientId":286747531,"TescoBaseProductId":78229008,"Image":"https://img.tesco.com/Groceries/pi/320/5054402551320/IDShot_110x110.jpg","TescoPermanentlyUnavailable":false,"PriceHistory":[{"Supermarket":0,"Price":2.4,"Checked":"2017-07-31T16:00:54.728785+01:00"},{"Supermarket":0,"Price":2.4,"Checked":"2017-08-01T10:26:03.665988+01:00"},{"Supermarket":0,"Price":2.4,"Checked":"2017-08-02T09:15:32.38087+01:00"},{"Supermarket":0,"Price":2.4,"Checked":"2017-08-03T09:07:44.222461+01:00"},{"Supermarket":0,"Price":2.4,"Checked":"2017-08-04T09:42:01.316583+01:00"}]}