{"EAN":"5411188119098","Name":"Alpro Big Pot Plain With Coconut Yoghurt Alternative 500G","TescoProductId":287042159,"TescoClientId":287042159,"TescoBaseProductId":78383515,"Image":"https://img.tesco.com/Groceries/pi/098/5411188119098/IDShot_110x110.jpg","TescoPermanentlyUnavailable":false,"PriceHistory":[{"Supermarket":0,"Price":1.8,"Checked":"2017-07-27T15:59:18.957409+01:00"},{"Supermarket":0,"Price":1.8,"Checked":"2017-07-28T14:28:39.970272+01:00"},{"Supermarket":0,"Price":1.8,"Checked":"2017-07-31T16:13:03.651271+01:00"},{"Supermarket":0,"Price":1.8,"Checked":"2017-08-01T10:27:13.459633+01:00"},{"Supermarket":0,"Price":1.8,"Checked":"2017-08-02T09:27:31.871025+01:00"}]}