{"EAN":"5054269038187","Name":"Tesco Ground Cloves 40G","TescoProductId":287841498,"TescoClientId":287841498,"TescoBaseProductId":78775150,"Image":"https://img.tesco.com/Groceries/pi/187/5054269038187/IDShot_110x110.jpg","TescoPermanentlyUnavailable":false,"PriceHistory":[{"Supermarket":0,"Price":0.85,"Checked":"2017-07-31T16:17:58.435071+01:00"},{"Supermarket":0,"Price":0.85,"Checked":"2017-08-01T10:31:06.736121+01:00"},{"Supermarket":0,"Price":0.85,"Checked":"2017-08-02T10:08:00.968954+01:00"},{"Supermarket":0,"Price":0.85,"Checked":"2017-08-03T09:30:48.909478+01:00"}]}