{"EAN":"4005900121226","Name":"Nivea Sun After Sun Bronze Tan Prolonger 200Ml","TescoProductId":287807880,"TescoClientId":287807880,"TescoBaseProductId":78759694,"Image":"https://img.tesco.com/Groceries/pi/226/4005900121226/IDShot_110x110.jpg","TescoPermanentlyUnavailable":false,"PriceHistory":[{"Supermarket":0,"Price":6.0,"Checked":"2017-08-08T15:43:56.711639+01:00"},{"Supermarket":0,"Price":6.0,"Checked":"2017-08-09T15:07:02.744135+01:00"},{"Supermarket":0,"Price":6.0,"Checked":"2017-08-10T13:00:32.922254+01:00"}]}