{"EAN":"0000003260531","Name":"Tesco Finest Clementine Or Sweet Easy Peeler 600G","TescoProductId":288115395,"TescoClientId":288115395,"TescoBaseProductId":78911934,"Image":"https://img.tesco.com/Groceries/pi/531/0000003260531/IDShot_110x110.jpg","TescoPermanentlyUnavailable":false,"PriceHistory":[{"Supermarket":0,"Price":2.0,"Checked":"2017-07-27T15:58:23.880112+01:00"},{"Supermarket":0,"Price":2.0,"Checked":"2017-07-28T14:30:15.715589+01:00"},{"Supermarket":0,"Price":2.0,"Checked":"2017-08-01T10:32:41.726522+01:00"},{"Supermarket":0,"Price":2.0,"Checked":"2017-08-02T10:08:12.464178+01:00"},{"Supermarket":0,"Price":2.0,"Checked":"2017-08-03T10:25:13.019625+01:00"},{"Supermarket":0,"Price":2.0,"Checked":"2017-08-04T11:04:12.463826+01:00"},{"Supermarket":0,"Price":2.0,"Checked":"2017-08-07T10:06:35.625651+01:00"},{"Supermarket":0,"Price":2.0,"Checked":"2017-08-08T11:37:32.36231+01:00"}]}