{"EAN":"5054402955746","Name":"Tesco Frozen Strawberries Whole 350G","TescoProductId":290455657,"TescoClientId":290455657,"TescoBaseProductId":80090352,"Image":"https://img.tesco.com/Groceries/pi/746/5054402955746/IDShot_110x110.jpg","TescoPermanentlyUnavailable":false,"PriceHistory":[{"Supermarket":0,"Price":1.0,"Checked":"2017-07-27T11:15:47.467858+01:00"},{"Supermarket":0,"Price":1.0,"Checked":"2017-07-26T11:42:47.77886+01:00"},{"Supermarket":0,"Price":1.0,"Checked":"2017-07-25T11:04:45.023982+01:00"},{"Supermarket":0,"Price":1.0,"Checked":"2017-07-24T13:18:57.138122+01:00"},{"Supermarket":0,"Price":2.0,"Checked":"2017-07-23T21:49:09.72444+01:00"},{"Supermarket":0,"Price":2.0,"Checked":"2017-07-21T14:44:57.9669+01:00"},{"Supermarket":0,"Price":2.0,"Checked":"2017-07-21T14:44:48.254784+01:00"},{"Supermarket":0,"Price":2.0,"Checked":"2017-07-17T10:41:59.577566+01:00"},{"Supermarket":0,"Price":2.0,"Checked":"2017-07-17T10:42:33.509349+01:00"},{"Supermarket":0,"Price":2.0,"Checked":"2017-07-17T10:42:34.084986+01:00"},{"Supermarket":0,"Price":2.0,"Checked":"2017-07-17T10:43:07.851756+01:00"},{"Supermarket":0,"Price":2.0,"Checked":"2017-07-17T10:43:08.330275+01:00"},{"Supermarket":0,"Price":2.0,"Checked":"2017-07-17T10:43:08.058948+01:00"},{"Supermarket":0,"Price":2.0,"Checked":"2017-07-17T10:43:10.036676+01:00"},{"Supermarket":0,"Price":2.0,"Checked":"2017-07-17T11:17:10.657917+01:00"},{"Supermarket":0,"Price":2.0,"Checked":"2017-07-17T11:17:34.86131+01:00"},{"Supermarket":0,"Price":2.0,"Checked":"2017-07-17T11:17:35.87008+01:00"},{"Supermarket":0,"Price":2.0,"Checked":"2017-07-17T11:18:08.571009+01:00"},{"Supermarket":0,"Price":2.0,"Checked":"2017-07-17T11:18:09.541859+01:00"},{"Supermarket":0,"Price":2.0,"Checked":"2017-07-17T11:18:09.550362+01:00"},{"Supermarket":0,"Price":2.0,"Checked":"2017-07-17T11:18:13.549632+01:00"},{"Supermarket":0,"Price":2.0,"Checked":"2017-07-17T16:12:48.366271+01:00"},{"Supermarket":0,"Price":2.0,"Checked":"2017-07-17T16:12:50.755277+01:00"},{"Supermarket":0,"Price":2.0,"Checked":"2017-07-20T12:10:42.741783+01:00"},{"Supermarket":0,"Price":2.0,"Checked":"2017-07-20T15:19:33.150101+01:00"},{"Supermarket":0,"Price":2.0,"Checked":"2017-07-20T15:19:38.39123+01:00"},{"Supermarket":0,"Price":2.0,"Checked":"2017-07-20T17:13:48.472203+01:00"},{"Supermarket":0,"Price":2.0,"Checked":"2017-07-20T17:13:58.158206+01:00"}]}