{"EAN":"5016346115983","Name":"Thorntons Continental Chocolates 284G","TescoProductId":291358840,"TescoClientId":291358840,"TescoBaseProductId":80550678,"Image":"https://img.tesco.com/Groceries/pi/983/5016346115983/IDShot_110x110.jpg","TescoPermanentlyUnavailable":false,"PriceHistory":[{"Supermarket":0,"Price":9.0,"Checked":"2017-07-31T16:02:03.47367+01:00"},{"Supermarket":0,"Price":9.0,"Checked":"2017-08-01T10:44:10.019497+01:00"},{"Supermarket":0,"Price":9.0,"Checked":"2017-08-02T09:16:33.09591+01:00"},{"Supermarket":0,"Price":9.0,"Checked":"2017-08-03T09:09:25.779658+01:00"}]}