{"EAN":"5051873019892","Name":"Pizza Express Pollo Ad Astra Pizza 280 G","TescoProductId":291358771,"TescoClientId":291358771,"TescoBaseProductId":80550632,"Image":"https://img.tesco.com/Groceries/pi/892/5051873019892/IDShot_110x110.jpg","TescoPermanentlyUnavailable":false,"PriceHistory":[{"Supermarket":0,"Price":4.5,"Checked":"2017-07-17T11:17:18.631546+01:00"},{"Supermarket":0,"Price":4.5,"Checked":"2017-07-20T17:12:11.503952+01:00"},{"Supermarket":0,"Price":4.5,"Checked":"2017-07-24T13:19:51.896247+01:00"},{"Supermarket":0,"Price":2.25,"Checked":"2017-07-25T11:05:39.100305+01:00"},{"Supermarket":0,"Price":2.25,"Checked":"2017-07-26T11:44:30.93554+01:00"},{"Supermarket":0,"Price":2.25,"Checked":"2017-07-27T15:58:25.489328+01:00"},{"Supermarket":0,"Price":2.25,"Checked":"2017-07-28T14:33:55.843937+01:00"},{"Supermarket":0,"Price":2.25,"Checked":"2017-08-01T10:44:09.536266+01:00"},{"Supermarket":0,"Price":2.25,"Checked":"2017-08-02T10:10:36.629014+01:00"},{"Supermarket":0,"Price":2.25,"Checked":"2017-08-03T10:29:37.79599+01:00"},{"Supermarket":0,"Price":2.25,"Checked":"2017-08-04T11:08:20.179977+01:00"},{"Supermarket":0,"Price":2.25,"Checked":"2017-08-07T08:56:25.54188+01:00"}]}