{"EAN":"3014260090807","Name":"Oral-B 3D White Brilliance Medium Manual Toothbrush","TescoProductId":291376645,"TescoClientId":291376645,"TescoBaseProductId":80568675,"Image":"https://img.tesco.com/Groceries/pi/807/3014260090807/IDShot_110x110.jpg","TescoPermanentlyUnavailable":false,"PriceHistory":[{"Supermarket":0,"Price":1.5,"Checked":"2017-07-31T16:03:13.543779+01:00"},{"Supermarket":0,"Price":1.5,"Checked":"2017-08-01T10:44:29.058579+01:00"},{"Supermarket":0,"Price":1.5,"Checked":"2017-08-02T09:17:33.953007+01:00"},{"Supermarket":0,"Price":1.5,"Checked":"2017-08-03T09:10:57.643902+01:00"},{"Supermarket":0,"Price":1.5,"Checked":"2017-08-04T09:45:13.562379+01:00"}]}