{"EAN":"5060107338777","Name":"Ella's Kitchen Banana And Cinnamon Muesli 215G","TescoProductId":291314691,"TescoClientId":291314691,"TescoBaseProductId":80522194,"Image":"https://img.tesco.com/Groceries/pi/777/5060107338777/IDShot_110x110.jpg","PriceHistory":[{"Supermarket":0,"Price":2.7,"Checked":"2017-07-24T16:46:42.689718+01:00"},{"Supermarket":0,"Price":2.7,"Checked":"2017-07-23T21:50:48.909441+01:00"},{"Supermarket":0,"Price":2.7,"Checked":"2017-07-21T14:46:12.715063+01:00"},{"Supermarket":0,"Price":2.7,"Checked":"2017-07-17T10:42:50.190892+01:00"},{"Supermarket":0,"Price":2.7,"Checked":"2017-07-17T11:17:38.76716+01:00"},{"Supermarket":0,"Price":2.7,"Checked":"2017-07-17T16:13:54.644871+01:00"},{"Supermarket":0,"Price":2.7,"Checked":"2017-07-20T12:11:33.582849+01:00"},{"Supermarket":0,"Price":2.7,"Checked":"2017-07-20T15:20:06.573804+01:00"},{"Supermarket":0,"Price":2.7,"Checked":"2017-07-20T17:15:01.04661+01:00"}]}