{"EAN":"5000204779370","Name":"Kiwi Fresh Instant Woman Insoles X6","TescoProductId":292293879,"TescoClientId":292293879,"TescoBaseProductId":81028259,"Image":"https://img.tesco.com/Groceries/pi/370/5000204779370/IDShot_110x110.jpg","TescoPermanentlyUnavailable":false,"PriceHistory":[{"Supermarket":0,"Price":3.98,"Checked":"2017-07-31T16:20:06.762627+01:00"},{"Supermarket":0,"Price":3.98,"Checked":"2017-08-01T10:52:01.159694+01:00"},{"Supermarket":0,"Price":3.98,"Checked":"2017-08-02T10:11:47.602543+01:00"},{"Supermarket":0,"Price":3.98,"Checked":"2017-08-03T10:31:44.493564+01:00"},{"Supermarket":0,"Price":3.98,"Checked":"2017-08-04T11:10:23.063928+01:00"},{"Supermarket":0,"Price":3.98,"Checked":"2017-08-07T09:15:15.514618+01:00"},{"Supermarket":0,"Price":3.98,"Checked":"2017-08-09T15:32:46.485101+01:00"}]}