{"EAN":"5012836754670","Name":"Levi Roots Kit Jamaican Jerk Recipe Kit 150G","TescoProductId":293397156,"TescoClientId":293397156,"TescoBaseProductId":81562242,"Image":"https://img.tesco.com/Groceries/pi/670/5012836754670/IDShot_110x110.jpg","TescoPermanentlyUnavailable":false,"PriceHistory":[{"Supermarket":0,"Price":2.93,"Checked":"2017-07-31T16:19:36.79225+01:00"},{"Supermarket":0,"Price":2.93,"Checked":"2017-08-01T11:01:03.445134+01:00"},{"Supermarket":0,"Price":2.93,"Checked":"2017-08-02T09:34:18.784122+01:00"},{"Supermarket":0,"Price":2.93,"Checked":"2017-08-03T09:09:17.13904+01:00"},{"Supermarket":0,"Price":2.93,"Checked":"2017-08-04T09:43:33.666487+01:00"},{"Supermarket":0,"Price":2.93,"Checked":"2017-08-07T09:12:37.893912+01:00"}]}