{"EAN":"5057008392090","Name":"Tesco Cumberl& Sausages 20 Pack 900G","TescoProductId":293723318,"TescoClientId":293723318,"TescoBaseProductId":81722249,"Image":"https://img.tesco.com/Groceries/pi/090/5057008392090/IDShot_110x110.jpg","TescoPermanentlyUnavailable":false,"PriceHistory":[{"Supermarket":0,"Price":2.75,"Checked":"2017-07-20T17:16:45.607205+01:00"},{"Supermarket":0,"Price":2.75,"Checked":"2017-07-21T14:48:07.809365+01:00"},{"Supermarket":0,"Price":2.75,"Checked":"2017-07-24T13:23:35.508267+01:00"},{"Supermarket":0,"Price":2.75,"Checked":"2017-07-25T11:09:26.033698+01:00"},{"Supermarket":0,"Price":2.75,"Checked":"2017-07-26T11:51:01.286491+01:00"},{"Supermarket":0,"Price":2.75,"Checked":"2017-07-27T16:02:05.786191+01:00"},{"Supermarket":0,"Price":2.75,"Checked":"2017-07-28T14:38:49.587206+01:00"},{"Supermarket":0,"Price":2.75,"Checked":"2017-07-31T17:02:58.464884+01:00"},{"Supermarket":0,"Price":2.75,"Checked":"2017-08-01T11:04:12.365582+01:00"},{"Supermarket":0,"Price":2.75,"Checked":"2017-08-02T10:13:13.589231+01:00"},{"Supermarket":0,"Price":2.75,"Checked":"2017-08-03T09:26:54.301576+01:00"},{"Supermarket":0,"Price":2.75,"Checked":"2017-08-04T10:01:16.982768+01:00"}]}