{"EAN":"5057008852457","Name":"Tesco Charcoal Briquettes 5Kg","TescoProductId":293800129,"TescoClientId":293800129,"TescoBaseProductId":81784618,"Image":"https://img.tesco.com/Groceries/pi/457/5057008852457/IDShot_110x110.jpg","TescoPermanentlyUnavailable":true,"PriceHistory":[{"Supermarket":0,"Price":5.0,"Checked":"2017-07-17T16:13:48.910317+01:00"},{"Supermarket":0,"Price":5.0,"Checked":"2017-07-20T17:16:35.808597+01:00"},{"Supermarket":0,"Price":5.0,"Checked":"2017-07-21T14:54:14.593287+01:00"},{"Supermarket":0,"Price":5.0,"Checked":"2017-07-24T13:23:42.550652+01:00"},{"Supermarket":0,"Price":5.0,"Checked":"2017-07-25T11:09:38.246562+01:00"},{"Supermarket":0,"Price":5.0,"Checked":"2017-07-26T11:51:16.780845+01:00"}]}