{"EAN":"5021991941009","Name":"Clipper Green Tea 26 Tea Bags 50G","TescoProductId":295025970,"TescoClientId":295025970,"TescoBaseProductId":52344337,"Image":"https://img.tesco.com/Groceries/pi/009/5021991941009/IDShot_110x110.jpg","TescoPermanentlyUnavailable":false,"PriceHistory":[{"Supermarket":0,"Price":1.4,"Checked":"2017-07-31T16:00:53.271183+01:00"},{"Supermarket":0,"Price":1.4,"Checked":"2017-08-01T11:13:01.187828+01:00"},{"Supermarket":0,"Price":1.4,"Checked":"2017-08-02T09:15:32.38087+01:00"},{"Supermarket":0,"Price":1.4,"Checked":"2017-08-03T09:07:44.222461+01:00"},{"Supermarket":0,"Price":1.4,"Checked":"2017-08-04T09:42:04.721871+01:00"},{"Supermarket":0,"Price":1.4,"Checked":"2017-08-07T08:53:18.136979+01:00"}]}