{"EAN":"5998749131688","Name":"Pedigree Tasty Bites Chicken Puppy Treats 125G","TescoProductId":295226921,"TescoClientId":295226921,"TescoBaseProductId":82465382,"Image":"https://img.tesco.com/Groceries/pi/688/5998749131688/IDShot_110x110.jpg","TescoPermanentlyUnavailable":false,"PriceHistory":[{"Supermarket":0,"Price":1.5,"Checked":"2017-07-31T16:17:15.72186+01:00"},{"Supermarket":0,"Price":1.5,"Checked":"2017-08-01T11:15:24.421282+01:00"},{"Supermarket":0,"Price":1.5,"Checked":"2017-08-02T10:15:02.751562+01:00"},{"Supermarket":0,"Price":1.5,"Checked":"2017-08-03T10:37:50.782341+01:00"},{"Supermarket":0,"Price":1.5,"Checked":"2017-08-04T11:15:47.616605+01:00"},{"Supermarket":0,"Price":1.5,"Checked":"2017-08-07T10:02:32.036344+01:00"},{"Supermarket":0,"Price":1.5,"Checked":"2017-08-08T14:41:16.421242+01:00"}]}