{"EAN":"3600542048460","Name":"Garnier Skinactv Naturals Honey Wash 200Ml","TescoProductId":296639857,"TescoClientId":296639857,"TescoBaseProductId":83151875,"Image":"https://img.tesco.com/Groceries/pi/460/3600542048460/IDShot_110x110.jpg","TescoPermanentlyUnavailable":false,"PriceHistory":[{"Supermarket":0,"Price":2.33,"Checked":"2017-07-20T17:09:46.552429+01:00"},{"Supermarket":0,"Price":2.33,"Checked":"2017-07-21T14:41:19.674699+01:00"},{"Supermarket":0,"Price":2.33,"Checked":"2017-07-24T13:29:19.98738+01:00"},{"Supermarket":0,"Price":2.33,"Checked":"2017-07-25T11:15:26.459733+01:00"},{"Supermarket":0,"Price":2.33,"Checked":"2017-07-26T14:38:27.076969+01:00"},{"Supermarket":0,"Price":2.33,"Checked":"2017-07-27T15:58:27.034408+01:00"},{"Supermarket":0,"Price":2.33,"Checked":"2017-07-28T14:45:30.984414+01:00"},{"Supermarket":0,"Price":2.33,"Checked":"2017-07-31T17:06:11.339943+01:00"},{"Supermarket":0,"Price":2.33,"Checked":"2017-08-01T11:29:18.391118+01:00"},{"Supermarket":0,"Price":2.33,"Checked":"2017-08-02T10:17:07.472285+01:00"},{"Supermarket":0,"Price":2.33,"Checked":"2017-08-03T10:41:55.355267+01:00"},{"Supermarket":0,"Price":2.33,"Checked":"2017-08-04T11:19:51.746815+01:00"},{"Supermarket":0,"Price":2.33,"Checked":"2017-08-07T10:23:37.894079+01:00"},{"Supermarket":0,"Price":2.33,"Checked":"2017-08-08T14:31:45.906861+01:00"}]}